delta_density/__init__.py
delta_density/delta_density.py
delta_density-0.0.1.dist-info/LICENSE
delta_density-0.0.1.dist-info/METADATA
delta_density-0.0.1.dist-info/WHEEL
delta_density-0.0.1.dist-info/top_level.txt
delta_density-0.0.1.dist-info/RECORD
