Metadata-Version: 2.1
Name: delta_density
Version: 0.0.1
Summary: Implementation of delta-density equations
Author-email: Jakub Plesnik <jakub.plesnik@gmail.com>
Project-URL: Homepage, https://github.com/PlesnikJakub/delta-density
Classifier: Programming Language :: Python :: 3
Classifier: License :: OSI Approved :: MIT License
Classifier: Operating System :: OS Independent
Requires-Python: >=3.7
License-File: LICENSE
